{
	"animations": [
		{
			"loop": false,
			"offsets": [
				-4,
				30
			],
			"anim": "idle",
			"fps": 24,
			"name": "IDLE",
			"indices": []
		},
		{
			"loop": false,
			"offsets": [
				4,
				31
			],
			"anim": "singLEFT",
			"fps": 24,
			"name": "LEFT",
			"indices": []
		},
		{
			"loop": false,
			"offsets": [
				-28,
				90
			],
			"anim": "singUP",
			"fps": 24,
			"name": "UP",
			"indices": []
		},
		{
			"loop": false,
			"offsets": [
				-46,
				31
			],
			"anim": "singRIGHT",
			"fps": 24,
			"name": "RIGHT",
			"indices": []
		},
		{
			"offsets": [
				3,
				37
			],
			"loop": false,
			"fps": 24,
			"anim": "singLEFTmiss",
			"indices": [],
			"name": "MISSLEFT"
		},
		{
			"offsets": [
				-29,
				40
			],
			"loop": false,
			"fps": 24,
			"anim": "singDOWNmiss",
			"indices": [],
			"name": "MISSDOWN"
		},
		{
			"offsets": [
				-28,
				94
			],
			"loop": false,
			"fps": 24,
			"anim": "singUPmiss",
			"indices": [],
			"name": "MISSUP"
		},
		{
			"offsets": [
				-45,
				59
			],
			"loop": false,
			"fps": 24,
			"anim": "singRIGHTmiss",
			"indices": [],
			"name": "MISSRIGHT"
		},
		{
			"offsets": [
				47,
				34
			],
			"loop": false,
			"fps": 24,
			"anim": "singLEFT-alt",
			"indices": [],
			"name": "COOLLEFT"
		},
		{
			"offsets": [
				-20,
				-32
			],
			"loop": false,
			"fps": 24,
			"anim": "singDOWN-alt",
			"indices": [],
			"name": "COOLDOWN"
		},
		{
			"offsets": [
				-29,
				150
			],
			"loop": false,
			"fps": 24,
			"anim": "singUP-alt",
			"indices": [],
			"name": "COOLUP"
		},
		{
			"offsets": [
				-21,
				-6
			],
			"loop": false,
			"fps": 24,
			"anim": "singDOWN",
			"indices": [],
			"name": "DOWN"
		},
		{
			"offsets": [
				-10,
				20
			],
			"loop": false,
			"fps": 24,
			"anim": "singRIGHT-alt",
			"indices": [],
			"name": "COOLRIGHT"
		},
		{
			"loop": false,
			"offsets": [
				12,
				78
			],
			"anim": "dodge",
			"fps": 24,
			"name": "DODGE",
			"indices": []
		},
		{
			"loop": false,
			"offsets": [
				0,
				108
			],
			"anim": "hurt",
			"fps": 24,
			"name": "HIT",
			"indices": []
		}
	],
	"no_antialiasing": false,
	"image": "characters/CosBF",
	"position": [
		120,
		450
	],
	"healthicon": "bf",
	"flip_x": true,
	"healthbar_colors": [
		49,
		176,
		209
	],
	"camera_position": [
		110,
		-100
	],
	"sing_duration": 4,
	"scale": 2
}