{
	"animations": [
		{
			"offsets": [
				-3,
				0
			],
			"loop": true,
			"fps": 24,
			"anim": "idle",
			"indices": [],
			"name": "mario idle"
		},
		{
			"offsets": [
				143,
				-41
			],
			"loop": false,
			"fps": 24,
			"anim": "singLEFT",
			"indices": [],
			"name": "mario left"
		},
		{
			"offsets": [
				75,
				147
			],
			"loop": false,
			"fps": 24,
			"anim": "singUP",
			"indices": [],
			"name": "mario up"
		},
		{
			"offsets": [
				152,
				-41
			],
			"loop": false,
			"fps": 24,
			"anim": "singRIGHT",
			"indices": [],
			"name": "mario right"
		},
		{
			"offsets": [
				65,
				-180
			],
			"loop": false,
			"fps": 24,
			"anim": "singDOWN",
			"indices": [],
			"name": "mario down"
		},
		{
			"offsets": [
				81,
				196
			],
			"loop": false,
			"fps": 24,
			"anim": "fade",
			"indices": [],
			"name": "mario fade away"
		}
	],
	"no_antialiasing": false,
	"image": "characters/Too_Late_Mario",
	"position": [
		100,
		60
	],
	"healthicon": "latemario",
	"flip_x": false,
	"healthbar_colors": [
		183,
		63,
		38
	],
	"camera_position": [
		-210,
		-180
	],
	"sing_duration": 4,
	"scale": 2
}