{
	"animations": [
		{
			"loop": false,
			"offsets": [
				73,
				-12
			],
			"anim": "lol",
			"fps": 24,
			"name": "mario aplastado el crico",
			"indices": []
		},
		{
			"loop": false,
			"offsets": [
				0,
				0
			],
			"anim": "idle",
			"fps": 24,
			"name": "mashedmario idle",
			"indices": []
		},
		{
			"loop": false,
			"offsets": [
				21,
				-94
			],
			"anim": "singDOWN",
			"fps": 24,
			"name": "mashedmario down",
			"indices": []
		},
		{
			"loop": false,
			"offsets": [
				-19,
				1
			],
			"anim": "singRIGHT",
			"fps": 24,
			"name": "mashedmario right",
			"indices": []
		},
		{
			"loop": false,
			"offsets": [
				36,
				-19
			],
			"anim": "singLEFT",
			"fps": 24,
			"name": "mashedmario left",
			"indices": []
		},
		{
			"loop": false,
			"offsets": [
				-10,
				64
			],
			"anim": "singUP",
			"fps": 24,
			"name": "mashedmario up",
			"indices": []
		},
		{
			"loop": false,
			"offsets": [
				-1,
				31
			],
			"anim": "boton",
			"fps": 24,
			"name": "mashedmario boton",
			"indices": []
		}
	],
	"no_antialiasing": false,
	"image": "characters/mashedmario",
	"position": [
		140,
		220
	],
	"healthicon": "secret",
	"flip_x": false,
	"healthbar_colors": [
		57,
		88,
		127
	],
	"camera_position": [
		-330,
		-280
	],
	"sing_duration": 4,
	"scale": 1.9
}